construct_labs_crm_env/__init__.py
construct_labs_crm_env/client.py
construct_labs_crm_env/models.py
construct_labs_crm_env/protocol.py
construct_labs_crm_env/py.typed
construct_labs_crm_env/tools.py
construct_labs_crm_env-0.1.5.dist-info/METADATA
construct_labs_crm_env-0.1.5.dist-info/WHEEL
construct_labs_crm_env-0.1.5.dist-info/licenses/LICENSE
construct_labs_crm_env-0.1.5.dist-info/RECORD
