Metadata-Version: 2.4
Name: construct-labs-crm-env
Version: 0.1.5
Summary: CRM Agent Environment SDK by Construct Labs - Train RL agents to interact with CRM systems
Project-URL: Homepage, https://construct-labs.com
Author-email: Construct Labs GmbH <hello@construct-labs.com>
License: Proprietary
License-File: LICENSE
Keywords: agent,ai,crm,environment,machine-learning,reinforcement-learning
Classifier: Development Status :: 4 - Beta
Classifier: Intended Audience :: Developers
Classifier: Intended Audience :: Science/Research
Classifier: License :: Other/Proprietary License
Classifier: Operating System :: OS Independent
Classifier: Programming Language :: Python :: 3
Classifier: Programming Language :: Python :: 3.10
Classifier: Programming Language :: Python :: 3.11
Classifier: Programming Language :: Python :: 3.12
Classifier: Topic :: Scientific/Engineering :: Artificial Intelligence
Classifier: Typing :: Typed
Requires-Python: >=3.10
Requires-Dist: openenv-core>=0.2.0
Requires-Dist: pydantic>=2.0.0
Requires-Dist: websockets>=12.0
Provides-Extra: dev
Requires-Dist: mypy>=1.0.0; extra == 'dev'
Requires-Dist: pytest-asyncio>=0.21.0; extra == 'dev'
Requires-Dist: pytest>=7.0.0; extra == 'dev'
Requires-Dist: ruff>=0.1.0; extra == 'dev'
